setup.py
YahooJapanDataReader/__init__.py
YahooJapanDataReader.egg-info/PKG-INFO
YahooJapanDataReader.egg-info/SOURCES.txt
YahooJapanDataReader.egg-info/dependency_links.txt
YahooJapanDataReader.egg-info/requires.txt
YahooJapanDataReader.egg-info/top_level.txt
YahooJapanDataReader/io/__init__.py
YahooJapanDataReader/io/data.py