Metadata-Version: 1.0
Name: YahooJapanDataReader
Version: 0.0.4
Summary: Read japanese stock price and corporate profile data from Yahoo! Finance Japan.
Home-page: https://github.com/sawadyrr5/YahooJapanDataReader
Author: sawadyrr5
Author-email: riskreturn5@gmail.com
License: UNKNOWN
Platform: UNKNOWN
